{
  "site_name": "Monastir",
  "type": "city",
  "country": "Tunisia",
  "historical_era": null,
  "collected_date": "2025-11-22 19:56:44",
  "sources": [
    {
      "source": "Wikipedia-EN",
      "language": "en",
      "url": "https://en.wikipedia.org/wiki/Monastir",
      "title": "Monastir",
      "content": "Monastir may refer to:\n\nPlaces\nTunisia\nMonastir, Tunisia, the capital of Monastir Governorate\nMonastir Habib Bourguiba International Airport\nMonastir Governorate, one of the twenty-four governorates of Tunisia\n\nOther places\nManastir, Republic of North Macedonia, the former name of Bitola\nManastir vilayet, covering parts of modern Albania, Greece and North Macedonia\nMonastir, Sardinia, a comune in the Province of Cagliari, Italy\n\nOther uses\nUS Monastir, a football club from Monastir, Tunisia\n\nSee also\nManastir (disambiguation)\nMonastery",
      "summary": "Monastir may refer to:",
      "word_count": 75
    },
    {
      "source": "Wikipedia-AR",
      "language": "ar",
      "url": "https://ar.wikipedia.org/wiki/%D8%A7%D9%84%D9%85%D9%86%D8%B3%D8%AA%D9%8A%D8%B1",
      "title": "المنستير",
      "content": "المنستير مدينة تونسية ومركز ولاية المنستير، تعد واحدة من أهم مدن تونس. تبعد 21 كم عن سوسة و 80 كم عن القيروان. يقطنها نحو نصف مليون ساكن، وهي منتجع سياحي بامتياز، ومركز تعليمي بارز، ظلّت على مدى نصف قرن مدينة الوزراء والحكام في تونس، فمن بين 18 وزيرا في عهد بورقيبة منحت لمدينة الرئيس 15 حقيبة.\nكانت المدينة مستعمرة فينيقية تعرف بروسبينا أسسها مهاجرون من صور في نهاية القرن السادس ق.م تحديدا في عام 509 ق.م حيث ورد ذكر المدينة في المعاهدة التي عقدت بين القرطاجيين والرومان في ذلك العام. وقد اتخذها يوليوس قيصر كقاعدة عسكرية له.\n\nالتوأمة\nأبرمت مدينة المنستير عام 1969 اتفاقية توأمة مع مدينة مونستر الألمانية بتأثير التشابه في تاريخ المدينتين. إذ أسست المدينتين في ذات الوقت تقريبا من القرن الثامن. وفي كلا الحالتين كان بناء دير هو سبب إنشاء المدينة، الأمر الذي ما زال يظهر في اسمي المدينتين. فمونستر والمنستير هما تحريف للكلمة اللاتينية «monasterium» بمعنى دير. دخلت المدينتين إلى توأمة هدفها الرئيس هو التعاون من أجل التنمية ومن ضمنها التنمية الاقتصادية حيث تتركز التوأمة على مجالات الطب والاقتصاد والثقافة وخاصة الموسيقى.\n\nالتاريخ\nتسمية المنستير خصيصا جاءت لكثرة المعابد التي انتشرت في ربوع المدينة من برها إلى بحرها. واكتشفت العديد من القبور الصخرية داخل مغاوير يرجع عهدها إلى العهد الفينيقي وشبكة أنفاق كبرى تربط العديد من المدن ذات طابع ديني واستعملها الرومان والمسلمون ثانيا وأعادوا استعمالها وكثرت هذه القبور والمغاوير خصوصا في كل من جزيرة المائدة وجزيرة الوسطانية وجزيرة الغدامسي، وسمى تلك الجزر سكان المنستير. في ذلك الوقت باتت المدينة غير آهله نسبيا إذ كانت ماوى لرهبان والكهنة.\nيعود تأسيسها للقرن الرابع قبل الميلاد، حيث كانت تسمى في العهد الفينيقي بـ«روسبينا» وأطلق عليها اسم المنستير في العهد البيزنطي، ثم الروماني بعد سقوط قرطاج في 146 قبل الميلاد، بل قبل ذلك بمائة سنة، حيث خاض فيها يوليوس قيصر أول معاركه التي تكللت بالنجاح، وظلت تونس مستعمرة رومانية حتى قدوم الفاتحين المسلمين في العقد الخامس للهجرة الموافق للقرن السابع الميلادي، وقضوا على القائد الروماني جرجير، وطردوهم واتخذوا المنستير حصنا بحريا لحماية عاصمتهم القيروان.\n\nالتعليم\nالجامعة\nيحضر جامعة المنستير أكثر من 30 ألف طالب، وأكبر الكليات كلية العلوم تليها كلية العلوم الاقتصادية والتصرف ثم المعهد العالي للبيوتكنولوجيا، ويناهز عدد الأساتذة 2000. وتضم الجامعة 5 كليات و 9 معاهد عليا ومدرستين، أي مجموع 16 مؤسسة هي: كليات «الطب» و«العلوم» و«طب الأسنان» (الوحيدة بالجمهورية التونسية) و«الصيدلة» و«العلوم الاقتصادية والتصرف»، والمعهد التحضيري للدراسات الهندسية، والمعهد العالي للإعلامية، والمعهد العالي للإعلامية والرياضيات، والمعهد العالي للبيوتكنولوجيا والمعهد العالي للفنون والحرف، والمعهد العالي للدراسات التطبيقية والإنسانية، و المعهد العالي للغات المطبقة في الأعمال والسياحة، والمعهد العالي لمهن الموضة، والمعهد العالي للعولم التطبيقية والتكنولوجيا، والمدرسة الوطنية للمهندسين، المدرسة العليا لعلوم وتطبيقات الصحةالمدرسة العليا لعلوم وتطبيقات الصحة بالمنستير - بعضها بالمهدية ومساكن.\nوتضم جامعة المنستير 86 وحدة بحث علمي من بينها 31 بكلية الطب و 18 بكلية العلوم و 17 بكلية الصيدلة. كما تضم 12 مختبر بحث منها 5 بكلية العلوم.\n\nالمرافق\nتتمتع المنستير بميناء يتسع لأكثر من 400 حاوية ويتواجد به (مطار الحبيب بورقيبة الدولي) أحد أنشط مطارات الجمهورية التونسية.\n\nالسياحة\nالمنتجعات\nوتزخر بالكثير من النزل ومعظمها منتجعات سياحية، عددها بالمئات، وتستخدم الخيول والجمال للتنقل بينها، وتمتاز بالهدوء والنظافة، ينزلها أفواج سياحية من أوروبا وغيرها.\nمن بينها:\n\nمنتجع «أوريونت بالاس» الساحلي، به 5 مطاعم فاخرة ومتنوعة، تطل شرفات غرفها على البحر والطبيعة والشوارع الهادئة، وببعض غرفها مسابح.\n\nالكورنيش\nالكورنيش مرصوف بالآجر، وبه ضريح المازري، وترى منه جزر وتلال وسط البحر تضم أماكن للترفيه ومطاعم ومقاهي، كما تنتشر بامتداد الكورنيش، الذي يمتاز بالنظافة، ويزخر بالتحف المعمارية.\n\nالرباط\nرباط المنستير تراه من الكورنيش، أسسه هرثمة بن الأعين سنة 80 هـ (796 م) في عهد الخليفة العباسي هارون الرشيد، ويعد أحد أعظم المعالم العسكرية الدفاعية. كان حراسه من المتطوعين لحراسة الثغور، ويعرفون في الأدبيات الإسلامية التاريخية بـ«المرابطين في سبيل الله». وأدخلت على الرباط تحصينات كبيرة بين القرنين الـ15 والـ18. وترى من أعلى هرم في الرباط - والبالغ ارتفاعه نحو 20 مترا - منظراً عاماً لمدينة المنستير. كما تترائى ملامح جزيرتي سيدي غدامسي (نسبة لمدينة غدامس الليبية) والموستانية، وكذلك كهوف المنستير التاريخية التي تعود لأكثر من 4000 سنة المنحوتة فيها مساكن.\n\nالفنادق\nمن أشهر فنادق المنستير:\n\n«مونستير تسنتر» تحتوي غرفه الـ186 على جميع الخدمات الإعلامية، وتحيط بمسباحه كراس للاستلقاء.\n«فندق الصحراء» تطل غرفه التي تزيد على الألف على حدائق جميلة ويوفر أماكن لممارسة الهوايات المختلفة.\n«فندق مازري» يطل على البحر قريباً من المرسى، وقريب من المطار، وبه 52 غرفة نوم و 3 أجنحة، تمتاز بلوحات ورسوم متنوعة، ويتيح للزائر استئجار كوخ بحري من القش.\n«فندق طلاس فيليج سقانص» يقع على مساحة 15 هكتارا على الشاطئ، تحيط به حدائق، وغرفه الـ486 واسعة، وبه 5 مطاعم وملاعب ومركزا للعلاج.\n\nالأعلام\nولد في المدينة في 3 أغسطس 1903 رئيس الجمهورية التونسية الأول الحبيب بورقيبة وقد توفي ودُفِن فيها في 6 أبريل 2000. ووُلد فيها أيضا الطبيب والمناضل سالم الشاذلي.\n\n\n== المراجع ==",
      "summary": "المنستير مدينة تونسية ومركز ولاية المنستير، تعد واحدة من أهم مدن تونس. تبعد 21 كم عن سوسة و 80 كم عن القيروان. يقطنها نحو نصف مليون ساكن، وهي منتجع سياحي بامتياز، ومركز تعليمي بارز، ظلّت على مدى نصف قرن مدينة الوزراء والحكام في تونس، فمن بين 18 وزيرا في عهد بورقيبة منحت لمدينة الرئيس 15 حقيبة.\nكانت المدينة مستعمرة فينيقية تعرف بروسبينا أسسها مهاجرون من صور في نهاية القرن السادس ق.م تحديدا في عام 509 ق.م حيث ورد ذكر المدينة في المعاهدة التي عقدت بين القرطاجيين والرومان في ذلك العام. وقد اتخذها يوليوس قيصر كقاعدة عسكرية له.",
      "word_count": 769
    },
    {
      "source": "Wikipedia-FR",
      "language": "fr",
      "url": "https://fr.wikipedia.org/wiki/Monastir",
      "title": "Monastir",
      "content": "Monastir (arabe : منستير  [mʊnæstir]), est une ville côtière du Sahel tunisien, au centre-est de la Tunisie, située sur une presqu'île au sud-est du golfe d'Hammamet, à une vingtaine de kilomètres à l'est de Sousse et à 162 kilomètres au sud de Tunis. En 2014, la population de la municipalité atteint 93 306 habitants.\nLa ville est le chef-lieu du gouvernorat du même nom depuis 1974.\n\nToponymie\nLe nom de la ville proviendrait du mot « monastère » (monasterium en latin) même s'il reste un sujet de débat. Selon Hassan Hosni Abdelwaheb, le nom a une origine arabe, elle-même empruntée au terme grec monastrion, ayant la signification de monastère et répandu dans l'Empire byzantin pour décrire les forts bâtis sur le littoral méditerranéen. Avant la conquête musulmane et juste après le déclin de l'ancienne ville punico-romaine de Ruspina, Monastir est une ville bâtie par une communauté de moines chrétiens, reconnus par leur abbaye, qui occupent un monastère pleinement autonome. Après la conquête, les musulmans préservèrent le nom.\n\nGéographie\nLocalisation\nMonastir est une presqu'île entourée par la mer Méditerranée sur trois côtés et formant, vers le sud, le golfe du même nom, qui s'étend jusqu'au cap de Ras Dimass. Elle offre des paysages diversifiés, notamment ses plages sableuses et rocheuses ainsi qu'une falaise s'étendant sur près de six kilomètres.\n\nClimat\nHistoire\nDurant la Préhistoire, plusieurs civilisations se sont succédé dans la région. Les fouilles archéologiques montrent l'existence de traces de la civilisation atérienne qui a couvert la fin du Paléolithique moyen et le début du Paléolithique supérieur. La civilisation des Hawanet succède à la civilisation atérienne vers 3000-2000 av. J.-C.\nMonastir est bâtie sur les ruines de l'ancienne ville punico-romaine de Ruspina dont l'existence s'étend sur près de dix siècles, du IVe siècle av. J.-C. au VIe siècle apr. J.-C.. Ruspina qui signifie « presqu'île » représente un site stratégique à l'abri des incursions extérieures. Elle est connue pour avoir aidé le Carthaginois Hannibal Barca dans ses combats contre les Romains au IIIe siècle av. J.-C. Pendant la période romaine, Ruspina a un statut de ville libre ; c'est la première ville africaine à s'être alliée à Jules César, ce qui permet à ce dernier de s'y réfugier avec son armée en 46 av. J.-C. et de mener sa première bataille contre les Pompéiens, une alliance qui permet à la ville de prospérer et d'avoir un rang élevé.\nL'histoire musulmane de Monastir est étroitement liée à l'édification des ribats, mosquées et autres mausolées, ce qui confère à la région un aspect spirituel et intellectuel dont la renommée dépasse les frontières de l'Occident musulman. La ville est la première ville arabo-musulmane construite en Ifriqiya et sert à la défense du royaume aghlabide et à sa capitale Kairouan, choisie suffisamment loin de la côte pour éviter les assauts de la flotte byzantine contrôlant alors la mer Méditerranée.\n\nLors du conflit hispano-ottoman, qui dure tout au long du XVIe siècle, Monastir est la cible d'attaques des deux belligérants. La population réussit à éviter une annexion par les Espagnols en 1534 et la ville s'organise sous la forme d'une république populaire. Elle tombe cependant en 1550, avant d'être prise par les Ottomans en 1554 pour être rattachée à la régence de Tunis dès 1574. Dès le début de la présence ottomane en Tunisie, Monastir possède un caïdat, qui existait déjà sous les Hafsides, et qui jouit de toutes les prérogatives d'un gouverneur de province : il est chargé de l'administration générale, du maintien de la justice et de la charge lucrative de fermier des impôts ; il est aussi l'agent d'exécution du bey de Tunis.\nLaissée pour compte sous le protectorat français, Monastir retrouve son statut après l'indépendance, en devenant le chef-lieu du gouvernorat du même nom en 1974. Elle est la ville natale du premier président Habib Bourguiba, qui s'y fait construire de son vivant un mausolée dans lequel il est inhumé, ainsi qu'un palais présidentiel à proximité de la ville. La mosquée Bourguiba, datant de 1963, est aussi érigée en son honneur alors que l'aéroport international de Monastir porte également son nom.\nMonastir devient une importante ville universitaire. Avec Sousse et Sfax, la ville devient grâce à son port un point de transbordement pour le marché de l'huile d'olive. Elle est également, depuis les années 1960, l'un des centres les plus importants du secteur touristique tunisien, en particulier avec sa station balnéaire de Skanès.\nLors des événements de la révolution tunisienne de 2011, la prison civile de Monastir est incendiée dans la nuit du 14 au 15 janvier. Plus de quarante prisonniers y trouvent la mort.\n\nArchitecture et urbanisme\nLe ribat de Monastir est érigé par le wali Harthama Ibn Ayoun sur ordre du calife abbasside Hâroun ar-Rachîd en 796 comme moyen de défense contre les attaques de la flotte byzantine en Méditerranée. Il représente, avec le ribat de Sousse, l'une des deux forteresses les plus importantes de la côte du Sahel. D'après des messages relevant de l'histoire locale et datant du début du Xe siècle, c'est un mérite que de séjourner dans ce ribat connu sous le nom de Grande forteresse. Un service de garde de trois jours au ribat de Monastir est alors considéré comme une grande action religieuse, car les musulmans sont tenus de protéger leur patrie. Ce mérite était amplifié pendant les croisades.\nLa forteresse était perçue, aussi bien parmi les combattants que parmi les ascètes, comme un lieu de pèlerinage et de méditation pour les fêtes religieuses comme l'Achoura ou le ramadan. À l'étage supérieur de l'aile sud-est se trouvait une petite mosquée abritant un mihrab. Elle est aujourd'hui utilisée comme musée où sont exposés des objets provenant de la région ainsi que de Kairouan.\nParmi les monuments importants de la ville figure également la Grande Mosquée de Monastir, édifice en pierre de taille d'architecture sobre élevé au IXe siècle puis agrandi au cours des XIe et XVIIIe siècles.\n\nLa ville de Monastir abrite aussi un mausolée inauguré en 1963 par le président de l'époque, Habib Bourguiba. L'édifice, encadré par deux minarets de 25 mètres de hauteur, est surmonté d'un dôme doré qui est lui-même entouré de deux coupoles vertes. La porte d'entrée ainsi que la grille qui sépare celui-ci du reste du cimetière sont deux exemples de l'art tunisien.\n\nCulture\nPatrimoine culturel\nMonastir possède un musée des arts islamiques, inauguré le 5 août 1958 et qui est logé au premier étage de l'aile sud du ribat ; il comporte près de 300 œuvres (fragments de bois, stèles funéraires, céramiques lustrées, etc.) et reçoit chaque année la visite de presque 100 000 visiteurs.\nLe festival d'été de Monastir est organisé annuellement au sein du ribat et se poursuit pendant une période de trois à quatre semaines, offrant de nombreux spectacles musicaux, théâtraux et même cinématographiques.\nÀ quelques kilomètres du centre-ville, le centre culturel de Monastir fondé en 2000 accueille des manifestations culturelles diverses. En son sein, plusieurs associations culturelles dédiées principalement à la peinture, la musique et le théâtre y exercent leurs activités. Ce centre vient remplacer l'ancien centre culturel situé au cœur même de la ville ; il conserve quelques activités essentiellement estudiantines.\nL'Union des écrivains monastiriens est une association dont le local est situé dans la cité Chraka de l'ancienne ville. Elle accueille plusieurs membres et organise diverses rencontres culturelles.\n\nMusique\nL'ethnomusicologue et clarinettiste Hassine Haj Youssef figure parmi les personnalités les plus actives de Monastir dans le domaine musical. Disciple de Salah El Mahdi, il est aussi le père du violoniste et compositeur Jasser Haj Youssef. Il est professeur au Conservatoire national de Monastir et à l'Institut supérieur de musique de Sousse. Il a adapté la méthode de Zoltán Kodály à l'enseignement de la musique arabe, il est aussi producteur de plusieurs émissions de musique traditionnelle et d'anthropologie à Radio Monastir et à la télévision nationale.\nDepuis 2005, il consacre son temps à la composition et aux recherches sur les musiques soufies de Tunisie.\n\nHéraldique\nLe drapeau qui surmonte le blason au centre des armoiries de la ville (moitié blanc, moitié rouge avec un croissant bleu) est hissé sur le ribat de Monastir vers 1500.\n\nEnseignement\nLa ville de Monastir dénombre :\n\ncinq collèges de deuxième cycle de l'enseignement de base : Ali-Bourguiba, Moufida-Bourguiba Imtiez, Salem-Bchir et Pilote, compétent pour les gouvernorats de Monastir et Mahdia ;\nquatre lycées : Fatouma-Bourguiba (ancien lycée de garçons), Hédi-Khefacha, Bourguiba (ancien lycée de jeunes filles) et Pilote (ouvert depuis l'année scolaire 2003-2004).\nMonastir est par ailleurs le siège de l'Université de Monastir fondée le 2 septembre 2004 et qui couvre les gouvernorats de Monastir et Mahdia. Sur les seize établissements qui en dépendent, dix sont localisés à Monastir : \n\nles facultés des sciences, de médecine, de médecine dentaire et de pharmacie ;\nl'École nationale d'ingénieurs ;\nl'École supérieure des sciences et techniques de la santé ;\nles Instituts supérieurs de biotechnologie, d'informatique et de mathématiques et des métiers de la mode ;\nl'Institut préparatoire aux études d'ingénieurs.\n\nL'effectif des étudiants de Monastir dépasse 27 000 en 2007-2008, ce qui fait de la ville l'une des plus importantes en matière d'études universitaires avec Tunis, Sfax et Sousse.\n\nDialecte\nLe dialecte monastirien présente les caractéristiques du dialecte parlé dans l'ensemble du Sahel tunisien.\n\nGastronomie\nLa ville est connue pour plusieurs plats phares, notamment le couscous au cherkaw, auquel un festival local est dédié chaque été depuis 2004 ; celui-ci est organisé par une association spécifique sous le patronage du gouverneur. Le poisson salé, un plat préparé à base de poisson (généralement du mulet) dont on enlève les écailles et les arêtes avant de le bander dans du sel. Après quelques jours, le poisson est débarrassé du bandage et placé dans l'eau pour le désaler puis cuit à la vapeur accompagné de tomates pelées, de charmoula, d'harissa, de raisins secs et d'oignon ; il est consommé très souvent à l'occasion de la fête de l'Aïd el-Fitr.\nPour l'occasion des fêtes de mariage, un couscous spécial appelé smasem est cuisiné : il s'agit d'un couscous à la viande de bœuf, le nom étant en relation avec les parts généreuses de viande servies à côté de la semoule.\n\nPolitique\nLa municipalité de Monastir comporte un conseil municipal composé de trente membres. Les élections municipales du 9 mai 2010 ont conduit à la formation d'un conseil dont les membres appartiennent tous au Rassemblement constitutionnel démocratique (RCD), le parti au pouvoir au niveau national. La municipalité est divisée en quatre arrondissements : Médina Est, Médina Ouest, Skanès et Helya.\nPar ailleurs, de l'indépendance à 2011, tous les maires de Monastir appartiennent au parti au pouvoir sous des appellations diverses :\n\n1957-1963 : Habib Bourguiba\n1963-1980 : Habib Bourguiba Jr.\n1980-1985 : Hassen Bergaoui\n1985-1986 : Mohamed Ameur Ghedira\n1986-1990 : Néji Skhiri\n1990-1995 : Mohamed Mohsen Guetari\n1995-2005 : Mohamed Gorsane\n2005-2010 : Mohamed Besbès\n2010-2011 : Mondher Marzouk\n2011-2016 : Ali Mzali (par intérim, délégation spéciale)\ndepuis 2016 : Nabil Hmida (délégation spéciale)\nAu niveau national, un seul député issu de la liste du RCD, majoritaire aux élections du 25 octobre 2009, représente la ville de Monastir. Il s'agit de Mohamed Gorsane, ancien maire.\n\nSanté\nLa ville de Monastir est desservie par l'hôpital Fattouma-Bourguiba ainsi que le Centre International Carthage Médical, une polyclinique située dans la zone touristique de la ville.\n\nTransport\nTransport en commun\nLa ville de Monastir est desservie par le Métro du Sahel avec cinq stations sur son territoire : Les Hôtels, Aéroport Skanès-Monastir, La Faculté, Monastir (Gare Habib-Bourguiba) et Zone industrielle.\n\nTransport aérien\nMonastir est desservie par l'aéroport international de Monastir Habib-Bourguiba.\n\nÉconomie\nLa ville de Monastir accueille le siège de la compagnie aérienne Nouvelair Tunisie situé dans la zone touristique de Dkhila.\n\nSport\nMonastir dispose d'un stade de football, le stade Mustapha-Ben-Jannet, où évolue l'Union sportive monastirienne. La salle omnisports Mohamed-Mzali de Monastir, troisième salle couverte du pays avec une capacité d'accueil de 4 075 places, y est inaugurée le 8 avril 2006.\nOutre l'ancienne salle omnisports existent des terrains découverts de basket-ball et de handball ainsi que trois terrains annexes de football. Une piscine couverte accueille le club de natation alors que le Tennis Club de Monastir occupe les terrains de tennis du stade municipal[Quoi ?] où se déroule à plusieurs reprises un tournoi international junior[Quoi ?] ; un autre club de tennis occupe les terrains du complexe touristique El Habib. Le complexe sportif accueille aussi d'autres activités comme le sport féminin, le football en salle et les arts martiaux.\n\nJumelages\nLa ville de Monastir est jumelée avec la ville de Münster (Allemagne) depuis le 11 mars 1969.\n\nPersonnalités liées\nNotes et références\nBibliographie\nMohamed Bergaoui, Monastir, fragments d'histoire : avec plus de 100 illustration du vieux Monastir, Tunis, À compte d'auteur, 1997, 132 p. (ISBN 978-9973177865).\nMohamed Salah Sayadi, Monastir : essai d'histoire sociale du XIXe siècle, Tunis, Imprimerie La Presse, 1979, 528 p. (OCLC 799698960).\nSlimane Mostafa Zbiss, Inscriptions de Monastir, Tunis, Imprimerie La Presse, 1960 (OCLC 256405618).\nSlimane Mostafa Zbiss, Monastir : ses monuments, Tunis, Secrétariat d'État aux Affaires culturelles, 1964, 55 p. (OCLC 434006191).\n\nLiens internes\nÉglise de Monastir\n\nLiens externes\n\nSite officiel\n\n Portail de la Tunisie   Portail de la mer Méditerranée",
      "summary": "Monastir (arabe : منستير  [mʊnæstir]), est une ville côtière du Sahel tunisien, au centre-est de la Tunisie, située sur une presqu'île au sud-est du golfe d'Hammamet, à une vingtaine de kilomètres à l'est de Sousse et à 162 kilomètres au sud de Tunis. En 2014, la population de la municipalité atteint 93 306 habitants.\nLa ville est le chef-lieu du gouvernorat du même nom depuis 1974.",
      "word_count": 2188
    },
    {
      "source": "Wikivoyage",
      "language": "en",
      "url": "https://en.wikivoyage.org/wiki/Monastir",
      "content": "## Overview\nMonastir is a city in Tunisia 160 km from Tunis. Set along a superb coastline with a blue sea and long golden sandy beaches, Monastir is a pleasant seaside resort, a historical town full of tradition and one of the best tourist destinations in Northern Africa.\nUnder the protection of its ribat, one of the most impressive fortresses of Tunisia, Monastir's medina, fishing port, marina and background of villages and orchards make it a lively and welcoming destination.\n\n## Understand\nSituated halfway between Sousse and Mahdia, and in the intersection of Kairouan and El Jem, Monastir is distinguished by its location in the central coast of Tunisia. It is an ancient city dating from Phoenician times. Due to its strategic location, it shelters the oldest and the most important ribat in the Maghreb: a lovely fortress that is one of Tunisia's finest examples of Islamic military architecture.\nMonastir is also known as a really beautiful and calm city.\n\n## By plane\nMonastir is a three-hour flight from many principal European cities.\n35.7583310.7547221 Monastir Habib Bourguiba International Airport (MIR  IATA), Skanes (9 km from the city center), ☏ +216 73 521 300.\nGetting to the airport: the trip by taxi costs about 5 DT. Getting to the airport is also possible through train between Monastir and Sousse, since \"Skanes-Monastir airport station\" is 200 m from airport terminal.\n\n## By train\nThere are regular train services to Tunis and Sousse to the north and Mahdia to the south.\n35.770810.82642 Monastir railway station (Gare Habib Bourguiba Monastir).      (updated Jul 2022)\n\n## By bus\nA louage to Sousse takes about 20 minutes and costs 2.1 DT. It departs just outside of the medina walls next to the train station.\n35.773210.8256853 Gare Routière de Monastir.    (updated Nov 2018)\n\n## Get around\nThe distances between the Medina, Ribat and Marina are small enough to be covered on foot. Taxis for longer distances within the city can be found everywhere and are very cheap (less than DT3 for a trip within the city).\n\n## See\n35.776210.83291 Ribat. This fortified monastery is located next to the sea and provides a great visit with most of the ruins open to clamber over. It may be familiar as it has been used in several films as a stand in for Jerusalem, most notably Monty Python's Life of Brian. You can climb the tower and have a nice view over the coastline and city. 8 DT.      (updated Feb 2018)\nRibat also houses 35.7760110.8330682 Islamic Arts Museum of Monastir. Contains illuminated manuscripts, Coptic textiles from the fourth to seventh century, textiles from the ninth century, the Fatimid glass of tenth and eleventh centuries, Abbasid pottery, coins of gold and silver from the tenth and eleventh centuries and especially unique: an Arabic astrolabe made in Cordoba in 927 CE. Price included in Ribat entrance fee.  (updated Nov 2018)\n35.777710.82853 Mausoleum of Habib Bourguiba, Skanes, ☏ +216 71 341 077. Enormous mausoleum, in the centre of a large cemetery. It holds the remains of former president Habib Bourguiba, the father of Tunisian independence, who died on April 6, 2000. Free.      (updated Feb 2018)\n35.77818710.7827534 Museum of Habib Bourguiba, Palais Presidentiel de Skanes. It's a house of Habib Bourguiba, Tunisia's first president, which was later turned into a museum. It's worth a visit only if you're interested in the modern history of Tunisia, otherwise nothing spectacular.    (updated Nov 2018)\n35.77417510.8309685 Museum of folk arts and traditions of Monastir (Musée des arts et traditions populaires). Displays traditional Tunisian costumes: wedding costumes, adornments, woven domestic items and copper objects.    (updated Nov 2018)\n35.7706310.841646 The Old Port el Kahlia. Old port with excellent location and panoramic views.    (updated Nov 2018)\n35.779810.83347 Marina. Admiring looks, enormous yachts, floating restaurants and luxury hotels. It's also a nice place for a stroll in the sun and for a coffee. Free.    (updated Feb 2018)\n35.669910.89268 Great Mosque of Monastir. Built in the 9th century and then enlarged over the centuries. It now includes a prayer room and a minaret, and doesn't have a courtyard inside. Off-limits to non-Muslims.      (updated Nov 2018)\n35.77176310.8405839 Zaouia of Sidi Mansour Ba Yazid. Mausoleum of 17th-century Muslim mystic.    (updated Nov 2018)\n35.787210.8338410 Ancient ruins, Ghdamsi island.    (updated Nov 2018)\n\n## Further away\n35.67736710.87759911 Lamta Archaeological Museum, Avenue Habib Bourguiba, Lamta. Tu-Su 9AM–1PM and 4–7PM. The ancient city of Leptiminus is located about 10 km south of Monastir. It was founded by Phoenician sailors around the 12th century BC. The modern city of Lamta was built on top of this ancient city, thus leaving almost nothing of it. Although some remnants from the times of Leptiminus can still be found in this museum.      (updated Nov 2018)\n35.67621410.87986812 Ribat Lamta. 9AM–6PM.    (updated Nov 2018)\n35.62553710.89863113 Museum of Moknine (Musee Archeologique de Moknine), Moknine. Tu-Su 9:30AM–4:30PM.    (updated Nov 2018)\n\n## Do\n35.77442910.834291 Bicycle rental. 5 DT/hour.    (updated Nov 2018)\n35.75998610.7286432 Karting, Airport Road, Tourist Area (near Sahara Beach Hotel), ☏ +216 23400004, karting-monastir@hotmail.com. 10:00 - 02:00 in summer and 09:30 - 19:30 in the rest of the year. The Palm Karting Monastir offers a great deal for those who are passionate for karting or those who want to try it. Two circuits (adults and kids), a coffee shop, a great Mexican restaurant and a nice party space. 15 minutes/20 DT and 30 minutes/30 DT.    (updated Nov 2018)\nCarriage. You can also go around Monastir with the famous and traditional carriages and of course for a good price.\nTouristic train. It is a cheap and original means to discover the city.\n35.7457810.799843 Flamingo Golf Course, Route de Ouardanine B.P. 40, ☏ +216 73 500 283.    (updated Nov 2018)\n35.7778210.690214 Palm Links Golf Course, ☏ +216 73 521 910. Designed by Californian architect.    (updated Nov 2018)\n\n## Buy\n35.77343910.8293751 Medina. Only a small section of the original Medina remains but it contains a bazaar selling the usual souvenirs, artisanal jewelry, pottery and carpets. Prices seemed to be generally lower than in nearby Sousse.    (updated Nov 2018)\n35.77239710.8307792 Monoprix. 8:30AM–10PM. A large supermarket near the southeast wall of the Medina. You can buy everything here, including alcohol (wine/beer) at the back entrance. Next to Monoprix is a small local market for meat, vegetables, bread, etc.    (updated Nov 2018)\n\n## Budget\n35.76842210.8299721 Mix Max Tandoori, rue moufida bourguiba, R6.    (updated Sep 2022)\n35.76610610.8299962 Mamma Chami.    (updated Sep 2022)\n\n## Mid-range\n35.77982510.8313593 restaurant Marina The Captain, cap marina.    (updated Sep 2022)\n35.76807510.8301034 Guilty.    (updated Sep 2022)\n35.77468210.8293645 El koojina, Bab El Kram n°6.    (updated Aug 2022)\n35.76568610.826866 Soprano.    (updated Sep 2022)\n35.77021310.8294757 BIZZ'ART.    (updated Sep 2022)\n35.77909910.832238 Restaurant Bel Air Central.    (updated Sep 2022)\n\n## Splurge\n10.82194610.7592176 Royal Thalassa Monastir, Skanes, ☏ +216 73 520520, fax: +216 73520500. The only hotel with 5 stars in town. From 250 DT double.    (updated Mar 2017)\n\n## Sleep\nThe infrastructure of hotels is of a remarkable quality and continues to get even better. Classed hotels (from one to five stars) are beyond reproach for hygiene and facilities. Covered swimming pools, sporting facilities, mini-clubs for children and spa centers are very common.\n35.76443710.7345611 Amir Palace, Dkhila, ☏ +216 73 520 900, fax: +216 73 521 823. 4-star hotel. From 100 DT double.    (updated Mar 2017)\n35.76254410.7500232 Dessole Bella Vista, Zone Touristique Dkhila Skanes, ☏ +216 73 520 555, fax: +216 73 521 477. 4-star hotel.\n35.7727410.8370773 Delphin Ribat Hotel Monastir (El Habib), Av Habib Bourguiba, ☏ +216 73 466750, fax: +216 73 466751. 3-star hotel. From 100 DT double.\n35.7812810.8333464 Marina Cap Monastir - Appart Hôtel, Port Marina Monastir, ☏ +216 73 462 305. Nice studio apartments in the Marina with sea view, private bathroom and small kitchen. You can get a bargain price when booking online through one of the common hotel portals. From 80 DT.    (updated Nov 2018)\n35.78300610.692655 El Mouradi Skanes Hotel. A great hotel close to the beach. It is not a cheap hotel but it is worth the price. From 100 TN.    (updated Nov 2018)\n\n## Go next\nSousse\nKairouan\nEl Jem",
      "word_count": 1330
    }
  ]
}